view_all/__init__.py
learn_quick-0.0.1.dist-info/METADATA
learn_quick-0.0.1.dist-info/WHEEL
learn_quick-0.0.1.dist-info/license.txt
learn_quick-0.0.1.dist-info/top_level.txt
learn_quick-0.0.1.dist-info/RECORD
