Metadata-Version: 2.1
Name: learn-quick
Version: 0.0.1
Summary: A Simplest Explanation of ML algorithms
Home-page: 
Author: Gaurav Goswami,seyjuti Banerjee
Author-email: piyush.goswami888@gmail.com
License: MIT
Keywords: education,learning
Classifier: Development Status :: 5 - Production/Stable
Classifier: Intended Audience :: Education
Classifier: Operating System :: Microsoft :: Windows :: Windows 10
Classifier: License :: OSI Approved :: MIT License
Classifier: Programming Language :: Python :: 3
License-File: license.txt
